{
    "histroys": [
        {
            "since": "2.1.15",
            "overloads": [
                {
                    "parameters": [
                        {
                            "name": "regexp",
                            "types": [
                                "RegExp"
                            ]
                        },
                        {
                            "name": "keySelector",
                            "types": [
                                "function",
                                "string",
                                "symbol",
                                "number"
                            ],
                            "defaultValue": "defaultSelector",
                            "declare": {
                                "returns": {
                                    "type": "string"
                                },
                                "parameters": [
                                    {
                                        "name": "element",
                                        "types": [
                                            "any"
                                        ]
                                    },
                                    {
                                        "name": "index",
                                        "types": [
                                            "number"
                                        ]
                                    }
                                ]
                            }
                        }
                    ],
                    "returns": {
                        "type": "function",
                        "declare": {
                            "returns": {
                                "type": "boolean"
                            },
                            "parameters": [
                                {
                                    "name": "element",
                                    "types": [
                                        "any"
                                    ]
                                },
                                {
                                    "name": "index",
                                    "types": [
                                        "number"
                                    ]
                                }
                            ]
                        }
                    },
                    "description": "获取一个正则筛选器",
                    "remarks": [
                        "返回一个筛选器函数, 比较通过指定的 selector 映射传入的参数值后的值是否与匹配指定的正则表达式"
                    ],
                    "sees": [
                        {
                            "guide": "comparer"
                        },
                        {
                            "apis": "Enumerable.selectors",
                            "property": "default"
                        }
                    ]
                }
            ]
        }
    ]
}